lorenz_zonoid.py
lorenz_zonoid-0.0.9.dist-info/METADATA
lorenz_zonoid-0.0.9.dist-info/WHEEL
lorenz_zonoid-0.0.9.dist-info/top_level.txt
lorenz_zonoid-0.0.9.dist-info/RECORD
