Metadata-Version: 2.1
Name: lorenz-zonoid
Version: 0.0.9
Summary: Computes the Shapley Lorenz Zonoid share of covariates
Home-page: https://github.com/roye10/ShapleyLorenz
Author: Roman Enzmann
Author-email: ryenzmann@hotmail.com
License: MIT
Keywords: shapley lorenz zonoid
Platform: UNKNOWN
Classifier: Programming Language :: Python :: 3
Classifier: Programming Language :: Python :: 3.6
Classifier: Programming Language :: Python :: 3.7
Classifier: License :: OSI Approved :: MIT License
Classifier: Operating System :: OS Independent
Requires-Dist: numpy
Requires-Dist: scipy
Requires-Dist: tqdm
Requires-Dist: matplotlib
Provides-Extra: dev
Requires-Dist: pytest (>=3.7) ; extra == 'dev'
